odoo/addons/stock_inventory_lockdown/README.rst
odoo/addons/stock_inventory_lockdown/__init__.py
odoo/addons/stock_inventory_lockdown/__manifest__.py
odoo/addons/stock_inventory_lockdown/i18n/ca.po
odoo/addons/stock_inventory_lockdown/i18n/cs_CZ.po
odoo/addons/stock_inventory_lockdown/i18n/de.po
odoo/addons/stock_inventory_lockdown/i18n/es.po
odoo/addons/stock_inventory_lockdown/i18n/es_ES.po
odoo/addons/stock_inventory_lockdown/i18n/es_MX.po
odoo/addons/stock_inventory_lockdown/i18n/fi.po
odoo/addons/stock_inventory_lockdown/i18n/fr.po
odoo/addons/stock_inventory_lockdown/i18n/gl.po
odoo/addons/stock_inventory_lockdown/i18n/hr.po
odoo/addons/stock_inventory_lockdown/i18n/it.po
odoo/addons/stock_inventory_lockdown/i18n/nl_NL.po
odoo/addons/stock_inventory_lockdown/i18n/pt.po
odoo/addons/stock_inventory_lockdown/i18n/pt_BR.po
odoo/addons/stock_inventory_lockdown/i18n/ro.po
odoo/addons/stock_inventory_lockdown/i18n/sl.po
odoo/addons/stock_inventory_lockdown/i18n/stock_inventory_lockdown.pot
odoo/addons/stock_inventory_lockdown/i18n/tr.po
odoo/addons/stock_inventory_lockdown/i18n/tr_TR.po
odoo/addons/stock_inventory_lockdown/i18n/vi_VN.po
odoo/addons/stock_inventory_lockdown/i18n/zh_CN.po
odoo/addons/stock_inventory_lockdown/models/__init__.py
odoo/addons/stock_inventory_lockdown/models/stock_inventory.py
odoo/addons/stock_inventory_lockdown/models/stock_location.py
odoo/addons/stock_inventory_lockdown/models/stock_move_line.py
odoo/addons/stock_inventory_lockdown/readme/CONTRIBUTORS.md
odoo/addons/stock_inventory_lockdown/readme/DESCRIPTION.md
odoo/addons/stock_inventory_lockdown/readme/USAGE.md
odoo/addons/stock_inventory_lockdown/static/description/icon.png
odoo/addons/stock_inventory_lockdown/static/description/index.html
odoo/addons/stock_inventory_lockdown/static/images/move_error.png
odoo/addons/stock_inventory_lockdown/tests/__init__.py
odoo/addons/stock_inventory_lockdown/tests/test_stock_inventory_lockdown.py
odoo_addon_stock_inventory_lockdown-18.0.1.0.0.2.dist-info/METADATA
odoo_addon_stock_inventory_lockdown-18.0.1.0.0.2.dist-info/WHEEL
odoo_addon_stock_inventory_lockdown-18.0.1.0.0.2.dist-info/top_level.txt
odoo_addon_stock_inventory_lockdown-18.0.1.0.0.2.dist-info/RECORD
